twittergeo/__init__.py
twittergeo/cli.py
twittergeo/twittergeo.py
twittergeo-0.2.1.dist-info/DESCRIPTION.rst
twittergeo-0.2.1.dist-info/METADATA
twittergeo-0.2.1.dist-info/RECORD
twittergeo-0.2.1.dist-info/WHEEL
twittergeo-0.2.1.dist-info/entry_points.txt
twittergeo-0.2.1.dist-info/metadata.json
twittergeo-0.2.1.dist-info/top_level.txt
