Metadata-Version: 2.0
Name: twittergeo
Version: 0.2.1
Summary: Export Twitter searches to GeoJSON
Home-page: https://github.com/fitnr/twittergeo
Author: Neil Freeman
Author-email: contact@fakeisthenewreal.org
License: GNU General Public License v3 (GPLv3)
Keywords: twitter geo cli
Platform: UNKNOWN
Classifier: Development Status :: 4 - Beta
Classifier: Intended Audience :: Developers
Classifier: License :: OSI Approved :: GNU General Public License v3 (GPLv3)
Classifier: Natural Language :: English
Classifier: Operating System :: Unix
Classifier: Programming Language :: Python :: 2.7
Classifier: Programming Language :: Python :: 3.4
Classifier: Programming Language :: Python :: 3.5
Classifier: Operating System :: OS Independent
Requires-Dist: twitter-bot-utils (>=0.10.2)
